yaml_letta/__init__.py
yaml_letta/builder.py
yaml_letta/config.py
yaml_letta/factory.py
yaml_letta/parser.py
yaml_letta-0.1.0.dist-info/licenses/LICENSE
yaml_letta-0.1.0.dist-info/METADATA
yaml_letta-0.1.0.dist-info/WHEEL
yaml_letta-0.1.0.dist-info/entry_points.txt
yaml_letta-0.1.0.dist-info/top_level.txt
yaml_letta-0.1.0.dist-info/RECORD
